Stopwatch.srcs/sources_1/new/smg.v
`timescale 1ns / 1ps
//////////////////////////////////////////////////////////////////////////////////
// Company: 
// Engineer: 
// 
// Create Date: 2025/12/26 01:11:37
// Design Name: 
// Module Name: smg
// Project Name: 
// Target Devices: 
// Tool Versions: 
// Description: 
// 
// Dependencies: 
// 
// Revision:
// Revision 0.01 - File Created
// Additional Comments:
// 
//////////////////////////////////////////////////////////////////////////////////


module smg(
    input clk,
    input rst,
    input [15:0] dispdata,
    output reg [ 7:0] seg,
    output reg [ 3:0] an);
    reg [16:0] divclk_cnt;
    reg divclk;
    reg [3:0] disp_dat; //要显示的数据
    reg [1:0] disp_bit; //要显示的位
    parameter maxcnt = 16'd50000;
    always@(posedge clk or negedge rst)
    begin
        if(!rst)
        begin
            divclk <= 1'b0;
            divclk_cnt <= 17'd0;
        end
        else if(divclk_cnt == maxcnt)
        begin
            divclk <= ~divclk;
            divclk_cnt <= 17'd0;
        end
        else
        begin
            divclk_cnt <= divclk_cnt + 1'b1;
        end
    end
    always@(posedge divclk or negedge rst)
    begin
        if(!rst)
        begin
            an <= 4'b0000;
            disp_bit <= 2'd0;
        end
        else
        begin
            disp_bit <= disp_bit + 1'b1;
            case(disp_bit)
                2'h0:
                begin
                    disp_dat <= dispdata[3:0];
                    an <= 4'b0001;
                end
                2'h1:
                begin
                    disp_dat <= dispdata[7:4];
                    an <= 4'b0010;
                end
                2'h2:
                begin
                    disp_dat <= dispdata[11:8];
                    an <= 4'b0100;
                end
                2'h3:
                begin
                    disp_dat <= dispdata[15:12];
                    an <= 4'b1000;
                end
            endcase
        end
    end
    always@(disp_dat)
    begin
        case(disp_dat)
            4'h0: seg = 8'h3f;
            4'h1: seg = 8'h06;
            4'h2: seg = 8'h5b;
            4'h3: seg = 8'h4f;
            4'h4: seg = 8'h66;
            4'h5: seg = 8'h6d;
            4'h6: seg = 8'h7d;
            4'h7: seg = 8'h07;
            4'h8: seg = 8'h7f;
            4'h9: seg = 8'h6f;
            4'ha: seg = 8'h77;
            4'hb: seg = 8'h7c;
            4'hc: seg = 8'h39;
            4'hd: seg = 8'h5e;
            4'he: seg = 8'h79;
            4'hf: seg = 8'h71;
        endcase
    end
endmodule

Stopwatch.srcs/sources_1/new/key_debounce.v
`timescale 1ns / 1ps
//////////////////////////////////////////////////////////////////////////////////
// Company: 
// Engineer: 
// 
// Create Date: 2025/12/26 01:15:54
// Design Name: 
// Module Name: key_debounce
// Project Name: 
// Target Devices: 
// Tool Versions: 
// Description: 
// 
// Dependencies: 
// 
// Revision:
// Revision 0.01 - File Created
// Additional Comments:
// 
//////////////////////////////////////////////////////////////////////////////////


module key_debounce (
    input btn_clk,
    input rst,
    input [1:0]btn_in,
    output [1:0]btn_out);
    reg [1:0]btn0;
    reg [1:0]btn1;
    reg [1:0]btn2;
    assign btn_out = btn0 & btn1 & btn2;
    always@ (posedge btn_clk or negedge rst)
    begin
        if(!rst)
        begin
            btn0 <= 1'b0;
            btn1 <= 1'b0;
            btn2 <= 1'b0;
        end
        else
        begin
            btn0 <= btn_in;
            btn1 <= btn0;
            btn2 <= btn1;
        end
    end
endmodule

Stopwatch.srcs/sources_1/new/count_ctrl.v
`timescale 1ns / 1ps
//////////////////////////////////////////////////////////////////////////////////
// Company: 
// Engineer: 
// 
// Create Date: 2025/12/26 01:11:37
// Design Name: 
// Module Name: smg
// Project Name: 
// Target Devices: 
// Tool Versions: 
// Description: 
// 
// Dependencies: 
// 
// Revision:
// Revision 0.01 - File Created
// Additional Comments:
// 
//////////////////////////////////////////////////////////////////////////////////

module count_ctrl(
    input start_stop,
    input clk,
    input rst,
    output [23:0] disp_time);
 
    reg [19:0] divclk_cnt;
    reg divclk;
    reg [3:0] msec_l;
    reg [3:0] msec_h; 
    reg [3:0] sec_l;
    reg [3:0] sec_h;
    reg [3:0] min_l;
    reg [3:0] min_h;
    reg state;
    assign disp_time = {min_h, min_l, sec_h, sec_l, msec_h, msec_l};
    
    always @(posedge clk or posedge rst) begin
        if (!rst) begin
            state <= 2'b00;
        end else if (start_stop) begin  // 按钮按下
            case (state)
                2'b00: state <= 2'b01;  // 空闲 -> 运行
                2'b01: state <= 2'b10;  // 运行 -> 暂停
                2'b10: state <= 2'b01;  // 暂停 -> 运行
                default: state <= 2'b00;
            endcase
        end
    end
    
    always@(posedge clk or negedge rst)
    begin
        if(!rst)
        begin
            divclk <= 1'b0;
            divclk_cnt <= 20'd0;
        end
        else if(divclk_cnt == 20'd500000 - 1'b1)
        begin
            divclk <= ~divclk;
            divclk_cnt <= 20'd0;
        end
        else
        begin
            divclk_cnt <= divclk_cnt + 1'b1;
        end
    end
    always@(posedge divclk or negedge rst)
    begin
        if(!rst)
        begin
            msec_l <= 4'd0; 
            msec_h <= 4'd0;
            sec_l <= 4'd0; 
            sec_h <= 4'd0; 
            min_l <= 4'd0; 
            min_h <= 4'd0; 
        end
        else if(state == 2'b01)
        begin
            msec_l <= msec_l + 1'b1;
            if(msec_l == 4'd9)
            begin
                msec_l <= 4'd0;
                msec_h <= msec_h + 1'b1;
                if(msec_h == 4'd9)
                begin
                    msec_h <= 4'd0;
                    sec_l <= sec_l +1'b1;
                    if(sec_l == 4'd9)
                    begin
                        sec_l <= 4'd0;
                        sec_h <= sec_h + 1'b1;
                        if(sec_h == 4'd5)
                        begin
                            sec_h <= 4'd0;
                            min_l <= min_l +1'b1;
                            if(min_l == 4'd9)
                            begin
                                min_l <= 4'd0;
                                min_h <= min_h + 1'b1;
                                if(min_h == 4'd5)
                                begin
                                    min_h <= 4'd0;
                                end
                            end
                        end
                    end
                end
            end
        end
    end 
endmodule

Stopwatch.srcs/sources_1/new/Stopwatch.v
`timescale 1ns / 1ps
//////////////////////////////////////////////////////////////////////////////////
// Company: 
// Engineer: 
// 
// Create Date: 2025/12/26 01:18:28
// Design Name: 
// Module Name: Stopwatch
// Project Name: 
// Target Devices: 
// Tool Versions: 
// Description: 
// 
// Dependencies: 
// 
// Revision:
// Revision 0.01 - File Created
// Additional Comments:
// 
//////////////////////////////////////////////////////////////////////////////////


module Stopwatch(
    input [1:0]btn_in,
    input clk,
    output [7:0]seg_R4,
    output [7:0]seg_L2,
    output [7:0]an
    );
    wire [23:0]disp_time;
    wire [1:0]btn_out;
    reg [7:0]an_reg;
    count_ctrl c_ctrl(
        .start_stop(btn_out[1]),
        .clk(clk),
        .rst(~btn_in[0]),
        .disp_time(disp_time));
    key_debounce key_d(
        .btn_clk(clk),
        .rst(~btn_in[0]),
        .btn_in(btn_in),
        .btn_out(btn_out));
    smg smg_R4(
        .clk(clk),
        .rst(~btn_in[0]),
        .dispdata(disp_time[15:0]),
        .seg(seg_R4),
        .an(an[3:0]));
    smg smg_L2(
        .clk(clk),
        .rst(~btn_in[0]),
        .dispdata({8'b0,disp_time[23:16]}),
        .seg(seg_L2),
        .an(an[7:4]));
    
    initial begin
        an_reg = 8'b00111111;
         
    end
    always @(posedge clk) begin
        
    end
assign an = an_reg;      
endmodule

Stopwatch.srcs/sim_1/new/tb_stopwatch.v
`timescale 1ns / 1ps
//////////////////////////////////////////////////////////////////////////////////
// Company: 
// Engineer: 
// 
// Create Date: 2025/12/26 13:09:32
// Design Name: 
// Module Name: tb_stopwatch
// Project Name: 
// Target Devices: 
// Tool Versions: 
// Description: 
// 
// Dependencies: 
// 
// Revision:
// Revision 0.01 - File Created
// Additional Comments:
// 
//////////////////////////////////////////////////////////////////////////////////



//============================================
// 秒表系统仿真测试平台 (Vivado 2018.3)
// 测试功能：
// 1. 按键消抖功能
// 2. 启动/停止/复位控制
// 3. 计时精度验证
// 4. 数码管显示输出
// 5. 边界条件测试
//============================================
 

module tb_stopwatch;

    // 测试平台参数
    parameter CLK_PERIOD = 20;      // 50MHz时钟周期 = 20ns
    
    // 测试信号
    reg [1:0] btn_in = 2'b11;
    reg clk = 0;
    wire [7:0] seg_R4;
    wire [7:0] seg_L2;
    wire [7:0] an;
    
    // 测试统计
    integer test_count = 0;
    integer pass_count = 0;
    integer error_count = 0;
    
    // 测试阶段控制
    reg [3:0] test_phase = 0;
    reg [31:0] wait_counter = 0;
    
    // 实例化被测模块
    Stopwatch uut (
        .btn_in(btn_in),
        .clk(clk),
        .seg_R4(seg_R4),
        .seg_L2(seg_L2),
        .an(an)
    );
    
    // 时钟生成
    always #(CLK_PERIOD/2) clk = ~clk;
    
    // 主测试流程（状态机实现）
    initial begin
        $display("============================================");
        $display(" 秒表系统仿真测试开始 - 无task版本");
        $display("============================================");
        
        // 等待初始复位
        #CLK_PERIOD;
        
        // 测试阶段0：系统复位
        test_phase = 0;
        $display("\n[TEST %d] 执行系统复位...", test_count);
        btn_in[0] = 0;  // 按下复位
        #CLK_PERIOD;
        btn_in[0] = 1;  // 释放
        #CLK_PERIOD;
        
        if (uut.disp_time == 24'h000000) begin
            $display("[PASS] 计时器已清零");
            pass_count = pass_count + 1;
        end else begin
            $display("[FAIL] 计时器未清零，当前值：%h", uut.disp_time);
            error_count = error_count + 1;
        end
        test_count = test_count + 1;
        
        // 测试阶段1：按键消抖
        test_phase = 1;
        $display("\n[TEST %d] 测试按键消抖功能...", test_count);
        
        // 模拟机械抖动
        repeat(5) begin
            btn_in[1] = $random;
            #(CLK_PERIOD * 2);
        end
        
        // 稳定按键
        btn_in[1] = 1;
        repeat(10) @(posedge clk);
        
        if (uut.key_d.btn_out[1] == 1) begin
            $display("[PASS] 消抖后按键有效");
            pass_count = pass_count + 1;
        end else begin
            $display("[FAIL] 消抖功能异常");
            error_count = error_count + 1;
        end
        test_count = test_count + 1;
        
        // 测试阶段2：启动计时
        test_phase = 2;
        $display("\n[TEST %d] 启动计时器...", test_count);
        btn_in[1] = 0;  // 确保按键释放
        repeat(5) @(posedge clk);
        
        btn_in[1] = 1;  // 按下启动
        repeat(10) @(posedge clk);
        btn_in[1] = 0;  // 释放
        
        repeat(20) @(posedge clk);
        
        if (uut.c_ctrl.state == 2'b01) begin
            $display("[PASS] 计时器已启动");
            pass_count = pass_count + 1;
        end else begin
            $display("[FAIL] 状态机未进入运行状态，当前state=%b", uut.c_ctrl.state);
            error_count = error_count + 1;
        end
        test_count = test_count + 1;
        
        // 测试阶段3：计时精度（99ms）
        test_phase = 3;
        $display("\n[TEST %d] 验证计时精度到99ms...", test_count);
        wait(uut.disp_time >= 24'h000099);
        
        if (uut.disp_time == 24'h000099) begin
            $display("[PASS] 计时准确: %02d%02d:%02d%02d:%02d%02d", 
                     uut.c_ctrl.min_h, uut.c_ctrl.min_l,
                     uut.c_ctrl.sec_h, uut.c_ctrl.sec_l,
                     uut.c_ctrl.msec_h, uut.c_ctrl.msec_l);
            pass_count = pass_count + 1;
        end else begin
            $display("[FAIL] 计时错误");
            error_count = error_count + 1;
        end
        test_count = test_count + 1;
        
        // 测试阶段4：计时精度（1秒）
        test_phase = 4;
        $display("\n[TEST %d] 验证计时精度到1秒...", test_count);
        wait(uut.disp_time >= 24'h010000);
        
        if (uut.disp_time == 24'h010000) begin
            $display("[PASS] 计时准确: %02d:%02d:%02d", 
                     {uut.c_ctrl.min_h, uut.c_ctrl.min_l},
                     {uut.c_ctrl.sec_h, uut.c_ctrl.sec_l},
                     {uut.c_ctrl.msec_h, uut.c_ctrl.msec_l});
            pass_count = pass_count + 1;
        end else begin
            $display("[FAIL] 计时错误");
            error_count = error_count + 1;
        end
        test_count = test_count + 1;
        
        // 测试阶段5：停止计时
        test_phase = 5;
        $display("\n[TEST %d] 停止计时器...", test_count);
        btn_in[1] = 1;  // 按下停止
        repeat(10) @(posedge clk);
        btn_in[1] = 0;  // 释放
        
        repeat(20) @(posedge clk);
        
        if (uut.c_ctrl.state == 2'b10) begin
            $display("[PASS] 计时器已停止");
            pass_count = pass_count + 1;
        end else begin
            $display("[FAIL] 状态机未进入暂停状态");
            error_count = error_count + 1;
        end
        test_count = test_count + 1;
        
        // 测试阶段6：显示功能
        test_phase = 6;
        $display("\n[TEST %d] 验证数码管显示...", test_count);
        
        // 模拟数码管扫描周期
        repeat(10000) @(posedge clk);
        
        $display("[INFO] 右4位数码管段码: %h", seg_R4);
        $display("[INFO] 左2位数码管段码: %h", seg_L2);
        $display("[INFO] 位选信号: %b", an);
        
        pass_count = pass_count + 1;
        test_count = test_count + 1;
        
        // 测试阶段7：再次启动
        test_phase = 7;
        $display("\n[TEST %d] 重新启动计时器...", test_count);
        btn_in[1] = 1;  // 按下启动
        repeat(10) @(posedge clk);
        btn_in[1] = 0;  // 释放
        
        repeat(20) @(posedge clk);
        
        if (uut.c_ctrl.state == 2'b01) begin
            $display("[PASS] 计时器已重新启动");
            pass_count = pass_count + 1;
        end else begin
            $display("[FAIL] 重新启动失败");
            error_count = error_count + 1;
        end
        test_count = test_count + 1;
        
        // 测试阶段8：溢出测试（跳过等待）
        test_phase = 8;
        $display("\n[TEST %d] 测试溢出回零...", test_count);
        $display("[INFO] 手动设置接近溢出值...");
        
        // 直接设置接近溢出的值
        force uut.c_ctrl.min_h = 4'd5;
        force uut.c_ctrl.min_l = 4'd9;
        force uut.c_ctrl.sec_h = 4'd5;
        force uut.c_ctrl.sec_l = 4'd9;
        force uut.c_ctrl.msec_h = 4'd9;
        force uut.c_ctrl.msec_l = 4'd8;
        
        @(posedge uut.c_ctrl.divclk);
        
        release uut.c_ctrl.min_h;
        release uut.c_ctrl.min_l;
        release uut.c_ctrl.sec_h;
        release uut.c_ctrl.sec_l;
        release uut.c_ctrl.msec_h;
        release uut.c_ctrl.msec_l;
        
        if (uut.disp_time == 24'h000000) begin
            $display("[PASS] 溢出后正确回零");
            pass_count = pass_count + 1;
        end else begin
            $display("[FAIL] 溢出异常");
            error_count = error_count + 1;
        end
        test_count = test_count + 1;
        
        // 测试阶段9：最终显示验证
        test_phase = 9;
        $display("\n[TEST %d] 最终显示验证...", test_count);
        
        repeat(10) begin
            @(posedge uut.smg_R4.divclk);
            $display("[DISPLAY] 时间=%02d%02d:%02d%02d:%02d%02d | SEG_R4=%h | SEG_L2=%h | AN=%b",
                     uut.c_ctrl.min_h, uut.c_ctrl.min_l,
                     uut.c_ctrl.sec_h, uut.c_ctrl.sec_l,
                     uut.c_ctrl.msec_h, uut.c_ctrl.msec_l,
                     seg_R4, seg_L2, an);
        end
        
        pass_count = pass_count + 1;
        test_count = test_count + 1;
        
        // 测试完成总结
        #CLK_PERIOD;
        $display("\n============================================");
        $display(" 测试完成总结");
        $display("============================================");
        $display(" 总测试项: %d", test_count);
        $display(" 通过项: %d", pass_count);
        $display(" 失败项: %d", error_count);
        $display(" 通过率: %.1f%%", (pass_count*100.0)/test_count);
        $display("============================================");
        
        $finish;
    end
    
    // 波形监控
    initial begin
        $dumpfile("stopwatch_wave.vcd");
        $dumpvars(0, tb_stopwatch);
    end
    
endmodule

Stopwatch.sim/sim_1/behav/xsim/stopwatch_wave.vcd
$date
   Fri Dec 26 13:19:38 2025
$end
$version
  2018.3
$end
$timescale
  1ps
$end
$scope module tb_stopwatch $end
$var reg 2 ! btn_in [1:0] $end
$var reg 1 " clk $end
$var wire 8 # seg_R4 [7:0] $end
$var wire 8 $ seg_L2 [7:0] $end
$var wire 8 % an [7:0] $end
$var integer 32 & test_count $end
$var integer 32 ' pass_count $end
$var integer 32 ( error_count $end
$var reg 4 ) test_phase [3:0] $end
$var reg 32 * wait_counter [31:0] $end
$var parameter 32 + CLK_PERIOD [31:0] $end
$scope module uut $end
$var wire 2 , btn_in [1:0] $end
$var wire 1 - clk $end
$var wire 8 # seg_R4 [7:0] $end
$var wire 8 $ seg_L2 [7:0] $end
$var wire 8 % an [7:0] $end
$var wire 24 . disp_time [23:0] $end
$var wire 2 / btn_out [1:0] $end
$var reg 8 0 an_reg [7:0] $end
$scope module c_ctrl $end
$var wire 1 1 start_stop $end
$var wire 1 - clk $end
$var wire 1 2 rst $end
$var wire 24 . disp_time [23:0] $end
$var reg 20 3 divclk_cnt [19:0] $end
$var reg 1 4 divclk $end
$var reg 4 5 msec_l [3:0] $end
$var reg 4 6 msec_h [3:0] $end
$var reg 4 7 sec_l [3:0] $end
$var reg 4 8 sec_h [3:0] $end
$var reg 4 9 min_l [3:0] $end
$var reg 4 : min_h [3:0] $end
$var reg 1 ; state $end
$upscope $end
$scope module key_d $end
$var wire 1 - btn_clk $end
$var wire 1 < rst $end
$var wire 2 , btn_in [1:0] $end
$var wire 2 / btn_out [1:0] $end
$var reg 2 = btn0 [1:0] $end
$var reg 2 > btn1 [1:0] $end
$var reg 2 ? btn2 [1:0] $end
$upscope $end
$scope module smg_R4 $end
$var wire 1 - clk $end
$var wire 1 @ rst $end
$var wire 16 A dispdata [15:0] $end
$var reg 8 B seg [7:0] $end
$var reg 4 C an [3:0] $end
$var reg 17 D divclk_cnt [16:0] $end
$var reg 1 E divclk $end
$var reg 4 F disp_dat [3:0] $end
$var reg 2 G disp_bit [1:0] $end
$var parameter 16 H maxcnt [15:0] $end
$upscope $end
$scope module smg_L2 $end
$var wire 1 - clk $end
$var wire 1 I rst $end
$var wire 16 J dispdata [15:0] $end
$var reg 8 K seg [7:0] $end
$var reg 4 L an [3:0] $end
$var reg 17 M divclk_cnt [16:0] $end
$var reg 1 N divclk $end
$var reg 4 O disp_dat [3:0] $end
$var reg 2 P disp_bit [1:0] $end
$var parameter 16 Q maxcnt [15:0] $end
$upscope $end
$upscope $end
$upscope $end
$enddefinitions $end
#0
$dumpvars
b11 !
0"
bx #
bx $
b0xxxxxx %
b0 &
b0 '
b0 (
b0 )
b0 *
b10100 +
b11 ,
0-
b0 .
b0 /
b111111 0
01
02
b0 3
04
b0 5
b0 6
b0 7
b0 8
b0 9
b0 :
x;
0<
b0 =
b0 >
b0 ?
0@
b0 A
bx B
b0 C
b0 D
0E
bx F
b0 G
b1100001101010000 H
0I
b0 J
bx K
b0 L
b0 M
0N
bx O
b0 P
b1100001101010000 Q
$end
#10000
1"
1-
0;
#20000
b10 !
0"
b10 ,
0-
12
1<
1@
1I
#30000
1"
1-
b0 /
01
b1 3
b10 =
b1 D
b1 M
#40000
b11 !
0"
b11 ,
0-
b0 /
01
02
b0 3
b0 5
b0 6
b0 7
b0 8
b0 9
b0 :
0<
b0 =
0@
b0 D
0I
b0 M
#50000
1"
1-
#60000
b1 !
0"
b1 &
b1 '
b1 )
b1 ,
0-
#70000
1"
1-
#80000
0"
0-
#90000
1"
1-
#100000
b11 !
0"
b11 ,
0-
#110000
1"
1-
#120000
0"
0-
#130000
1"
1-
#140000
b11 !
0"
0-
#150000
1"
1-
#160000
0"
0-
#170000
1"
1-
#180000
b11 !
0"
0-
#190000
1"
1-
#200000
0"
0-
#210000
1"
1-
#220000
b11 !
0"
0-
#230000
1"
1-
#240000
0"
0-
#250000
1"
1-
#260000
b11 !
0"
0-
#270000
1"
1-
#280000
0"
0-
#290000
1"
1-
#300000
0"
0-
#310000
1"
1-
#320000
0"
0-
#330000
1"
1-
#340000
0"
0-
#350000
1"
1-
#360000
0"
0-
#370000
1"
1-
#380000
0"
0-
#390000
1"
1-
#400000
0"
0-
#410000
1"
1-
#420000
0"
0-
#430000
1"
1-
#440000
0"
0-
#450000
b1 !
1"
b10 &
b1 (
b10 )
b1 ,
1-
#460000
0"
0-
#470000
1"
1-
#480000
0"
0-
#490000
1"
1-
#500000
0"
0-
#510000
1"
1-
#520000
0"
0-
#530000
1"
1-
#540000
0"
0-
#550000
b11 !
1"
b11 ,
1-
#560000
0"
0-
#570000
1"
1-
#580000
0"
0-
#590000
1"
1-
#600000
0"
0-
#610000
1"
1-
#620000
0"
0-
#630000
1"
1-
#640000
0"
0-
#650000
1"
1-
#660000
0"
0-
#670000
1"
1-
#680000
0"
0-
#690000
1"
1-
#700000
0"
0-
#710000
1"
1-
#720000
0"
0-
#730000
1"
1-
#740000
0"
0-
#750000
b1 !
1"
b1 ,
1-
